xhpkg/__init__.py
xhpkg/init_project.py
xcpkg-0.0.1.dist-info/LICENSE
xcpkg-0.0.1.dist-info/METADATA
xcpkg-0.0.1.dist-info/WHEEL
xcpkg-0.0.1.dist-info/entry_points.txt
xcpkg-0.0.1.dist-info/top_level.txt
xcpkg-0.0.1.dist-info/RECORD
