Metadata-Version: 2.1
Name: xcpkg
Version: 0.0.1
Summary: 星辰包管理器。
Author-email: YeyingXingchen <yeyingxingchen@yeah.net>
License: MIT License
Keywords: xcpkg,package,manager
Requires-Python: >=3.12
License-File: LICENSE
